matfree/__init__.py
matfree/_version.py
matfree/bounds.py
matfree/decomp.py
matfree/eig.py
matfree/funm.py
matfree/low_rank.py
matfree/lstsq.py
matfree/stochtrace.py
matfree/test_util.py
matfree/backend/__init__.py
matfree/backend/config.py
matfree/backend/containers.py
matfree/backend/control_flow.py
matfree/backend/func.py
matfree/backend/linalg.py
matfree/backend/np.py
matfree/backend/plt.py
matfree/backend/prng.py
matfree/backend/testing.py
matfree/backend/time.py
matfree/backend/tree.py
matfree/backend/typing.py
matfree-0.5.4.dist-info/licenses/LICENSE
matfree-0.5.4.dist-info/METADATA
matfree-0.5.4.dist-info/WHEEL
matfree-0.5.4.dist-info/top_level.txt
matfree-0.5.4.dist-info/RECORD
