Metadata-Version: 2.4
Name: matfree
Version: 0.5.4
Summary: Matrix-free numerical linear algebra.
Author-email: Nicholas Krämer <pekra@dtu.dk>
Project-URL: Documentation, https://pnkraemer.github.io/matfree/
Project-URL: Issue tracker, https://github.com/pnkraemer/matfree/issues
Classifier: License :: OSI Approved :: MIT License
Classifier: Operating System :: OS Independent
Classifier: Programming Language :: Python
Classifier: Programming Language :: Python :: 3.11
Classifier: Programming Language :: Python :: 3.12
Classifier: Programming Language :: Python :: 3.13
Requires-Python: >=3.11
License-File: LICENSE
Provides-Extra: cpu
Requires-Dist: jax[cpu]; extra == "cpu"
Provides-Extra: test
Requires-Dist: pytest; extra == "test"
Requires-Dist: pytest-cases; extra == "test"
Provides-Extra: format-and-lint
Requires-Dist: matfree[test]; extra == "format-and-lint"
Requires-Dist: pre-commit; extra == "format-and-lint"
Provides-Extra: doc
Requires-Dist: mkdocs; extra == "doc"
Requires-Dist: mkdocs-material; extra == "doc"
Requires-Dist: mkdocstrings; extra == "doc"
Requires-Dist: mkdocstrings-python; extra == "doc"
Requires-Dist: mkdocs-jupyter; extra == "doc"
Requires-Dist: mkdocs-awesome-pages-plugin; extra == "doc"
Requires-Dist: matplotlib; extra == "doc"
Requires-Dist: tqdm; extra == "doc"
Provides-Extra: full
Requires-Dist: matfree[cpu]; extra == "full"
Requires-Dist: matfree[test]; extra == "full"
Requires-Dist: matfree[format-and-lint]; extra == "full"
Requires-Dist: matfree[doc]; extra == "full"
Dynamic: license-file
